Metadata-Version: 2.1
Name: paandass
Version: 0.1
Summary: Some aiml programs
Author: library
